bexy/__init__.py
bexy/api.py
bexy/app.py
bexy/bexy_run.py
bexy/code_analyzer.py
bexy/dependency_manager.py
bexy/docker_sandbox.py
bexy/examples.py
bexy/logging_config.py
bexy/python_sandbox.py
bexy/sandbox_manager.py
bexy/setup.py
bexy/utils.py
bexy/examples/api_request.py
bexy/examples/database.py
bexy/examples/default.py
bexy/examples/file_io.py
bexy/examples/web_server.py
bexy-0.1.26.dist-info/licenses/LICENSE
bexy-0.1.26.dist-info/METADATA
bexy-0.1.26.dist-info/WHEEL
bexy-0.1.26.dist-info/top_level.txt
bexy-0.1.26.dist-info/RECORD
