Metadata-Version: 2.4
Name: bexy
Version: 0.1.26
Summary: A sandbox for safely running Python code
Home-page: https://github.com/py-lama/bexy
Author: Tom Sapletta
Author-email: Tom Sapletta <info@softreck.dev>
License: Apache-2.0
Project-URL: Homepage, https://github.com/py-lama/bexy
Project-URL: Documentation, https://py-lama.github.io/bexy/
Project-URL: Repository, https://github.com/py-lama/bexy
Project-URL: Changelog, https://github.com/py-lama/bexy/blob/main/CHANGELOG.md
Project-URL: Tracker, https://github.com/py-lama/bexy/issues
Project-URL: Download, https://pypi.org/project/bexy/
Classifier: Development Status :: 3 - Alpha
Classifier: Intended Audience :: Developers
Classifier: License :: OSI Approved :: Apache Software License
Classifier: Programming Language :: Python :: 3
Classifier: Programming Language :: Python :: 3.8
Classifier: Programming Language :: Python :: 3.9
Classifier: Programming Language :: Python :: 3.10
Classifier: Programming Language :: Python :: 3.11
Classifier: Programming Language :: Python :: 3.12
Classifier: Topic :: Software Development :: Interpreters
Classifier: Topic :: Software Development :: Libraries :: Python Modules
Classifier: Topic :: Security
Requires-Python: >=3.8,<4.0
License-File: LICENSE
Dynamic: author
Dynamic: home-page
Dynamic: license-file
Dynamic: requires-python
